hardware/__init__.py
hardware/exceptions.py
hardware/opcodes.py
hardware/processor.py
hardware/reads.py
hardware/suboperation.py
hardware/instructions/__init__.py
hardware/instructions/accumulator.py
hardware/instructions/idx.py
hardware/instructions/idxacc.py
hardware/instructions/immediate.py
hardware/instructions/io_ram.py
hardware/instructions/memory_select.py
hardware/instructions/nop.py
hardware/instructions/subroutine.py
hardware/instructions/transfer_control.py
hardware/suboperations/__init__.py
hardware/suboperations/accumulator.py
hardware/suboperations/carry.py
hardware/suboperations/constants.py
hardware/suboperations/init.py
hardware/suboperations/other.py
hardware/suboperations/pc.py
hardware/suboperations/pin10.py
hardware/suboperations/ram.py
hardware/suboperations/registers.py
hardware/suboperations/rom.py
hardware/suboperations/stack.py
hardware/suboperations/utility.py
hardware/suboperations/wpm.py
Pyntel4004-1.2.dist-info/METADATA
Pyntel4004-1.2.dist-info/WHEEL
Pyntel4004-1.2.dist-info/top_level.txt
Pyntel4004-1.2.dist-info/RECORD
