Metadata-Version: 2.1
Name: Pyntel4004
Version: 1.2
Summary: A Python software implementation of the Intel 4004 processor.
Home-page: https://github.com/alshapton/Pyntel4004
Author: Andrew Shapton
Author-email: alshapton@gmail.com
Project-URL: Bug Tracker, https://github.com/alshapton/Pyntel4004/issues
Classifier: Programming Language :: Python
Classifier: Programming Language :: Python :: 3.8
Classifier: License :: OSI Approved :: MIT License
Classifier: Operating System :: OS Independent
Requires-Python: >=3.8
